pycomex/VERSION
pycomex/__init__.py
pycomex/config.py
pycomex/fix_config_bug.py
pycomex/fix_config_bug_README.md
pycomex/plugin.py
pycomex/testing.py
pycomex/util.py
pycomex/utils.py
pycomex/app/__init__.py
pycomex/cli/__init__.py
pycomex/cli/display.py
pycomex/cli/main.py
pycomex/cli/utils.py
pycomex/cli/commands/__init__.py
pycomex/cli/commands/archive.py
pycomex/cli/commands/run.py
pycomex/cli/commands/template.py
pycomex/examples/01_quickstart.py
pycomex/examples/02_basic.py
pycomex/examples/03_analysing.py
pycomex/examples/04_inheritance.py
pycomex/examples/05_testing_mode.py
pycomex/examples/06_run_experiment.py
pycomex/examples/07_meta_experiment.py
pycomex/examples/08_weights_and_biases.py
pycomex/examples/09_experiment_config.yml
pycomex/examples/10_caching.py
pycomex/examples/11_experiment_mixin.py
pycomex/examples/11_experiment_mixin_mixin.py
pycomex/examples/12_experiment_mixin.yml
pycomex/examples/README.rst
pycomex/examples/cli.py
pycomex/examples/test.py
pycomex/examples/test.yml
pycomex/examples/wordlist.txt
pycomex/functional/__init__.py
pycomex/functional/base.py
pycomex/functional/cache.py
pycomex/functional/experiment.py
pycomex/functional/mixin.py
pycomex/functional/parameter.py
pycomex/functional/testing.py
pycomex/functional/utils.py
pycomex/functional/validate.py
pycomex/plugins/notify/main.py
pycomex/plugins/plot_track/main.py
pycomex/plugins/weights_biases/main.py
pycomex/templates/analysis.ipynb
pycomex/templates/analysis.py.j2
pycomex/templates/annotations.py.j2
pycomex/templates/config.yml.j2
pycomex/templates/config_stub.py.j2
pycomex/templates/experiment.py.j2
pycomex/templates/experiment_ended.text.j2
pycomex/templates/experiment_extend.py.j2
pycomex/templates/experiment_info.out.j2
pycomex/templates/experiment_parameters.text.j2
pycomex/templates/experiment_started.text.j2
pycomex/templates/experiment_status.text.j2
pycomex/templates/functional_analysis.py.j2
pycomex/templates/functional_experiment_end.out.j2
pycomex-0.25.1.dist-info/METADATA
pycomex-0.25.1.dist-info/WHEEL
pycomex-0.25.1.dist-info/entry_points.txt
pycomex-0.25.1.dist-info/licenses/AUTHORS.rst
pycomex-0.25.1.dist-info/licenses/LICENSE
pycomex-0.25.1.dist-info/RECORD
