Metadata-Version: 2.4
Name: pycomex
Version: 0.25.1
Summary: Python Computational Experiments
Project-URL: Homepage, https://github.com/the16thpythonist/pycomex
Project-URL: Repository, https://github.com/the16thpythonist/pycomex
Project-URL: Documentation, https://pycomex.readthedocs.io
Project-URL: Issues, https://github.com/the16thpythonist/pycomex/issues
Author-email: Jonas Teufel <jonseb1998@gmail.com>
Maintainer-email: Jonas Teufel <jonseb1998@gmail.com>
License: MIT License
License-File: AUTHORS.rst
License-File: LICENSE
Keywords: academia,computational experiments,data science,machine learning
Classifier: Development Status :: 4 - Beta
Classifier: Intended Audience :: Developers
Classifier: Intended Audience :: Science/Research
Classifier: License :: OSI Approved :: MIT License
Classifier: Programming Language :: Python :: 3
Classifier: Programming Language :: Python :: 3.10
Classifier: Programming Language :: Python :: 3.11
Classifier: Programming Language :: Python :: 3.12
Classifier: Topic :: Scientific/Engineering
Classifier: Topic :: Software Development :: Libraries :: Python Modules
Classifier: Topic :: System :: Archiving
Requires-Python: >=3.8
Requires-Dist: click<9.0.0,>=8.0.0
Requires-Dist: desktop-notifier<6.0.0,>=5.0.1
Requires-Dist: jinja2<4.0.0,>=3.0.3
Requires-Dist: joblib<2.0.0,>=1.2.0
Requires-Dist: matplotlib<4.0.0,>=3.5.3
Requires-Dist: moviepy<2.0.0,>=1.0.3
Requires-Dist: numpy<2.0.0,>=1.22.0
Requires-Dist: prettytable<4.0.0,>=3.7.0
Requires-Dist: psutil<6.0.0,>=5.7.2
Requires-Dist: pydantic<3.0.0,>=2.9.0
Requires-Dist: pyyaml<7.0.0,>=6.0
Requires-Dist: rich-argparse<2.0.0,>=1.0.0
Requires-Dist: rich-click<1.9.0,>=1.8.5
Requires-Dist: setuptools<=81.0.0
Requires-Dist: uv<0.5.0,>=0.4.0
Provides-Extra: dev
Requires-Dist: black<25.0,>=24.3; extra == 'dev'
Requires-Dist: mkdocs-material<10.0,>=9.5; extra == 'dev'
Requires-Dist: nox[uv]<2026.0,>=2025.0; extra == 'dev'
Requires-Dist: pre-commit<4.0,>=3.5; extra == 'dev'
Requires-Dist: pytest-cov<5.0,>=4.0; extra == 'dev'
Requires-Dist: pytest<8.0,>=7.0; extra == 'dev'
Requires-Dist: ruff<0.3,>=0.2; extra == 'dev'
